check_bacula/__init__.py
check_bacula/check_bacula.py
check_bacula-1.0.0.dist-info/DESCRIPTION.rst
check_bacula-1.0.0.dist-info/entry_points.txt
check_bacula-1.0.0.dist-info/METADATA
check_bacula-1.0.0.dist-info/metadata.json
check_bacula-1.0.0.dist-info/pbr.json
check_bacula-1.0.0.dist-info/RECORD
check_bacula-1.0.0.dist-info/top_level.txt
check_bacula-1.0.0.dist-info/WHEEL
