Metadata-Version: 2.0
Name: check-bacula
Version: 1.0.0
Summary: This tool checks the status of the backup jobs on a Bacula server.
Home-page: https://github.com/exonet/check-bacula
Author: Rick van den Hof
Author-email: r.vandenhof@exonet.nl
License: MIT
Platform: UNKNOWN
Classifier: Intended Audience :: Developers
Classifier: Intended Audience :: System Administrators
Classifier: Topic :: Utilities
Classifier: Environment :: Console
Classifier: License :: OSI Approved :: MIT License
Classifier: Programming Language :: Python
Classifier: Programming Language :: Python :: 2.7
Classifier: Operating System :: OS Independent
Classifier: Development Status :: 4 - Beta
Requires-Dist: MySQL-python
